task2/f1_fsm.sv
module f1_fsm (
    input logic rst,
    input logic en,
    input logic clk,
    output logic [7:0] data_out
);

    typedef enum {S0, S1, S2, S3, S4, S5, S6, S7, S8} my_state;
    my_state current_state, next_state;

    always_ff @ (posedge clk)
        if(rst) begin
            current_state <= S0;
        end
        else begin
            if (en) current_state <= next_state;
        end
    
    always_comb begin
        case (current_state)
            S0: if(en) next_state = S1;
            S1: if(en) next_state = S2;
            S2: if(en) next_state = S3;
            S3: if(en) next_state = S4;
            S4: if(en) next_state = S5;
            S5: if(en) next_state = S6;
            S6: if(en) next_state = S7;
            S7: if(en) next_state = S8;
        default: next_state = S0;
        endcase
    end

    always_comb
        case(current_state)
        S0: data_out = 8'b0;
        S1: data_out = 8'b1;
        S2: data_out = 8'b11;
        S3: data_out = 8'b111;
        S4: data_out = 8'b1111;
        S5: data_out = 8'b11111;
        S6: data_out = 8'b111111;
        S7: data_out = 8'b1111111;
        S8: data_out = 8'b11111111;
        default: data_out = 8'b0;
        endcase
endmodule

task2/f1_fsm.vcd
$version Generated by VerilatedVcd $end
$date Thu Nov  2 11:03:12 2023 $end
$timescale 1ps $end

 $scope module TOP $end
  $var wire  1 % clk $end
  $var wire  8 & data_out [7:0] $end
  $var wire  1 $ en $end
  $var wire  1 # rst $end
  $scope module f1_fsm $end
   $var wire  1 % clk $end
   $var wire 32 ' current_state [31:0] $end
   $var wire  8 & data_out [7:0] $end
   $var wire  1 $ en $end
   $var wire 32 ( next_state [31:0] $end
   $var wire  1 # rst $end
  $upscope $end
 $upscope $end
$enddefinitions $end


#0
1#
0$
1%
b00000000 &
b00000000000000000000000000000000 '
b00000000000000000000000000000000 (
#1
0%
#2
1%
#3
0%
#4
1%
#5
0%
#6
0#
1%
#7
0%
#8
1%
#9
0%
#10
1%
#11
0%
#12
1%
#13
0%
#14
1%
#15
0%
#16
1%
#17
0%
#18
1%
#19
0%
#20
1%
#21
0%
#22
1%
#23
0%
#24
1%
#25
0%
#26
1%
#27
0%
#28
1%
#29
0%
#30
1%
#31
0%
#32
1%
#33
0%
#34
1%
#35
0%
#36
1%
#37
0%
#38
1$
1%
#39
0%
b00000000000000000000000000000001 (
#40
0$
1%
b00000001 &
b00000000000000000000000000000001 '
b00000000000000000000000000000010 (
#41
0%
#42
1%
#43
0%
#44
1%
#45
0%
#46
1%
#47
0%
#48
1%
#49
0%
#50
1%
#51
0%
#52
1%
#53
0%
#54
1%
#55
0%
#56
1%
#57
0%
#58
1%
#59
0%
#60
1%
#61
0%
#62
1%
#63
0%
#64
1%
#65
0%
#66
1%
#67
0%
#68
1%
#69
0%
#70
1%
#71
0%
#72
1%
#73
0%
#74
1%
#75
0%
#76
1%
#77
0%
#78
1%
#79
0%
#80
1%
#81
0%
#82
1%
#83
0%
#84
1%
#85
0%
#86
1%
#87
0%
#88
1%
#89
0%
#90
1%
#91
0%
#92
1%
#93
0%
#94
1$
1%
#95
0%
#96
0$
1%
b00000011 &
b00000000000000000000000000000010 '
b00000000000000000000000000000011 (
#97
0%
#98
1%
#99
0%
#100
1%
#101
0%
#102
1%
#103
0%
#104
1%
#105
0%
#106
1%
#107
0%
#108
1%
#109
0%
#110
1%
#111
0%
#112
1%
#113
0%
#114
1%
#115
0%
#116
1%
#117
0%
#118
1%
#119
0%
#120
1%
#121
0%
#122
1%
#123
0%
#124
1%
#125
0%
#126
1%
#127
0%
#128
1$
1%
#129
0%
#130
0$
1%
b00000111 &
b00000000000000000000000000000011 '
b00000000000000000000000000000100 (
#131
0%
#132
1%
#133
0%
#134
1%
#135
0%
#136
1%
#137
0%
#138
1%
#139
0%
#140
1%
#141
0%
#142
1%
#143
0%
#144
1%
#145
0%
#146
1%
#147
0%
#148
1%
#149
0%
#150
1%
#151
0%
#152
1%
#153
0%
#154
1%
#155
0%
#156
1$
1%
#157
0%
#158
0$
1%
b00001111 &
b00000000000000000000000000000100 '
b00000000000000000000000000000101 (
